aimsgb/__init__.py
aimsgb/agb.py
aimsgb/grain.py
aimsgb/grain_bound.py
aimsgb/utils.py
tests/test_grain.py
tests/time/time.py
aimsgb-1.1.1.dist-info/METADATA
aimsgb-1.1.1.dist-info/WHEEL
aimsgb-1.1.1.dist-info/entry_points.txt
aimsgb-1.1.1.dist-info/top_level.txt
aimsgb-1.1.1.dist-info/RECORD
