Metadata-Version: 2.1
Name: aimsgb
Version: 1.1.1
Summary: aimsgb is a python library for generatng the atomic coordinates of periodic grain boundaries.Copyright © 2018 The Regents of the University of California.All Rights Reserved. See more in Copyright.
Home-page: http://aimsgb.org
Author: Jianli Cheng and Kesong YANG
Maintainer: Jianli Cheng, Sicong JIANG, and Kesong YANG
Maintainer-email: chengjianli90@gmail.com, sij014@ucsd.edu, kesong@ucsd.edu
Keywords: material science,grain boundary,molecular simulation
Classifier: Programming Language :: Python :: 3
Classifier: Programming Language :: Python :: 3.9
Classifier: Programming Language :: Python :: 3.10
Classifier: Development Status :: 4 - Beta
Classifier: Intended Audience :: Science/Research
Classifier: Operating System :: OS Independent
Classifier: Topic :: Scientific/Engineering :: Physics
Classifier: Topic :: Scientific/Engineering :: Chemistry
Classifier: Topic :: Software Development :: Libraries :: Python Modules
Requires-Python: >=3.9
Requires-Dist: pymatgen
Requires-Dist: mp-api
Requires-Dist: numpy
Requires-Dist: pytest
